htxbigdata/__init__.py
htxbigdata/apollo_utils.py
htxbigdata-0.0.2.dist-info/LICENSE.txt
htxbigdata-0.0.2.dist-info/METADATA
htxbigdata-0.0.2.dist-info/WHEEL
htxbigdata-0.0.2.dist-info/top_level.txt
htxbigdata-0.0.2.dist-info/RECORD
