Metadata-Version: 2.1
Name: htxbigdata
Version: 0.0.2
Summary: htx-bigdata-pypi-utils
Author: zhaozhenhua
Author-email: zhaozhenhua02@htx-inc.com
Classifier: Programming Language :: Python :: 3
Classifier: License :: OSI Approved :: MIT License
Classifier: Operating System :: OS Independent
Requires-Python: >=3.6
License-File: LICENSE.txt
